planarobot
