Metadata-Version: 1.1
Name: planarobot
Version: 0.0.6
Summary: Basic planar robotic arm with arbitrary number of links
Home-page: https://github.com/tsitsimis/planar-robot
Author: Theodore Tsitsimis
Author-email: th.tsitsimis@gmail.com
License: MIT
Download-URL: https://github.com/tsitsimis/planarobot/archive/0.0.6.tar.gz
Keywords: robotics,simulation,path-planning
Platform: UNKNOWN
Classifier: Development Status :: 3 - Alpha
Classifier: Intended Audience :: Developers
Classifier: Topic :: Software Development :: Build Tools
Classifier: License :: OSI Approved :: MIT License
Classifier: Programming Language :: Python :: 3
